QAgentLib/__init__.py
QAgentLib/agent.py
QAgentLib/environment.py
qagentlib-0.1.0.dist-info/licenses/LICENSE
qagentlib-0.1.0.dist-info/METADATA
qagentlib-0.1.0.dist-info/WHEEL
qagentlib-0.1.0.dist-info/top_level.txt
qagentlib-0.1.0.dist-info/RECORD
