Metadata-Version: 2.4
Name: QAgentLib
Version: 0.1.0
Summary: A reinforcement learning library inspired by Agentic Learn Pro, focusing on Q-learning.
Author-email: Ayorinde Alase <alaseayorinde@gmail.com>
Project-URL: Homepage, https://github.com/your_username/QAgentLib
Project-URL: Bug Tracker, https://github.com/your_username/QAgentLib/issues
Classifier: Programming Language :: Python :: 3
Classifier: License :: OSI Approved :: MIT License
Classifier: Operating System :: OS Independent
Classifier: Topic :: Scientific/Engineering :: Artificial Intelligence
Classifier: Topic :: Software Development :: Libraries :: Python Modules
Requires-Python: >=3.8
License-File: LICENSE
Requires-Dist: numpy
Dynamic: license-file
